nuimoctl.py
setup.py
nuimo/__init__.py
nuimo/nuimo.py
nuimo.egg-info/PKG-INFO
nuimo.egg-info/SOURCES.txt
nuimo.egg-info/dependency_links.txt
nuimo.egg-info/entry_points.txt
nuimo.egg-info/requires.txt
nuimo.egg-info/top_level.txt