Metadata-Version: 1.1
Name: nuimo
Version: 0.3.6
Summary: Nuimo SDK for Python on Linux
Home-page: https://github.com/getsenic/nuimo-linux-python
Author: Senic GmbH
Author-email: developers@senic.com
License: MIT
Download-URL: https://github.com/getsenic/nuimo-linux-python/archive/0.3.6.tar.gz
Keywords: nuimo
Platform: UNKNOWN
